lein_vector/__init__.py
lein_vector/api/__init__.py
lein_vector/api/facade.py
lein_vector/bases/__init__.py
lein_vector/bases/embeding_provider_abc.py
lein_vector/bases/memory_manager_abc.py
lein_vector/memory_manager_qdrant.py
lein_vector/memory_manager_ram.py
lein_vector/qdrant_adapter.py
lein_vector/redis_short_term.py
lein_vector/schemas/__init__.py
lein_vector/schemas/chunk.py
lein_vector/sentence_transformer.py
openvector_dev-0.1.33.dist-info/METADATA
openvector_dev-0.1.33.dist-info/WHEEL
openvector_dev-0.1.33.dist-info/RECORD
